[{
  "id": 1,
  "title": "Chinh Tri Xa Hoi",
  "description": ""
  },
  {"id": 2,
    "title": "Doi Song",
    "description": ""
  },
  { "id": 3,
    "title": "Khoa hoc",
    "description": ""
  },
  { "id": 4,
    "title": "Kinh doanh",
    "description": ""
  },
  { "id": 5,
    "title": "Phap luat",
    "description": ""
  },
  { "id": 6,
    "title": "Suc khoe",
    "description": ""
  },
  { "id": 7,
    "title": "The gioi",
    "description": ""
  },
  { "id": 8,
    "title": "The thao",
    "description": ""
  },
  { "id": 9,
    "title": "Van hoa",
    "description": ""
  },
  { "id": 10,
    "title": "Vi tinh",
    "description": ""
  }
]
